{"data":{"allFile":{"edges":[{"node":{"publicURL":"/static/toni-figuera-curriculum-castellano-75ce1e7b2dc49e07b0d65ba3c6c9c8b7.pdf","name":"toni-figuera-curriculum-castellano"}},{"node":{"publicURL":"/static/toni-figuera-curriculum-catala-550717de43653d21456cead86d681713.pdf","name":"toni-figuera-curriculum-catala"}}]},"allPageMappingsJson":{"edges":[{"node":{"pageUrlMappings":[{"es":"","ca":""},{"es":"curriculum","ca":"/curriculum"},{"es":"fotos","ca":"/fotos"},{"es":"contacto","ca":"/contacte"}]}}]},"site":{"siteMetadata":{"title":"Toni Figuera","siteUrl":"https://tonifiguera.com","name":"Toni","surname":"Figuera","copyright":"© 2019 Toni Figuera","instagramUsername":"tonifi","twitterUsername":"tonifi","fonts":"Playfair+Display:400,700|Source+Sans+Pro:300,400,600","languages":{"defaultLangKey":"es","langs":["es","ca"]}}}}}